sdxf.py
setup.py
dxf.egg-info/PKG-INFO
dxf.egg-info/SOURCES.txt
dxf.egg-info/dependency_links.txt
dxf.egg-info/top_level.txt