Metadata-Version: 1.0
Name: dxf
Version: 1.1.1
Summary: Python library to generate DXF drawing files (CAD)
Home-page: http://www.kellbot.com/sdxf-python-library-for-dxf/
Author: Stani <stanibe@gmail.com>, Kellbot <kellbot@kellbot.com>
Author-email: UNKNOWN
License: UNKNOWN
Platform: UNKNOWN
